topsis_simran_101803100/__init__.py
topsis_simran_101803100-1.0.2.dist-info/METADATA
topsis_simran_101803100-1.0.2.dist-info/WHEEL
topsis_simran_101803100-1.0.2.dist-info/licence.txt
topsis_simran_101803100-1.0.2.dist-info/top_level.txt
topsis_simran_101803100-1.0.2.dist-info/RECORD
