Metadata-Version: 2.1
Name: topsis-simran-101803100
Version: 1.0.2
Summary: Compare different models using performance score
Home-page: UNKNOWN
Author: Simran Jot Kaur
Author-email: simranjotkaur82@gmail.com
License: UNKNOWN
Platform: UNKNOWN
Classifier: Programming Language :: Python :: 3
Classifier: License :: OSI Approved :: MIT License
Classifier: Operating System :: OS Independent
